{".class": "MypyFile", "_fullname": "app.types", "is_partial_stub_package": false, "is_stub": false, "names": {".class": "SymbolTable", "Any": {".class": "SymbolTableNode", "cross_ref": "typing.Any", "kind": "Gdef"}, "Dict": {".class": "SymbolTableNode", "cross_ref": "typing.Dict", "kind": "Gdef"}, "HTML": {".class": "SymbolTableNode", "kind": "Gdef", "node": {".class": "TypeInfo", "_promote": null, "abstract_attributes": [], "bases": ["builtins.str"], "declared_metaclass": null, "defn": {".class": "ClassDef", "fullname": "app.types.HTML", "name": "HTML", "type_vars": []}, "flags": ["is_newtype"], "fullname": "app.types.HTML", "metaclass_type": null, "metadata": {}, "module_name": "app.types", "mro": ["app.types.HTML", "builtins.str", "typing.Sequence", "typing.Collection", "typing.Iterable", "typing.Container", "typing.Reversible", "builtins.object"], "names": {".class": "SymbolTable", "__init__": {".class": "SymbolTableNode", "kind": "Mdef", "node": {".class": "FuncDef", "arg_kinds": [0, 0], "arg_names": ["self", "item"], "flags": [], "fullname": "app.types.HTML.__init__", "name": "__init__", "type": {".class": "CallableType", "arg_kinds": [0, 0], "arg_names": ["self", "item"], "arg_types": ["app.types.HTML", "builtins.str"], "bound_args": [], "def_extras": {}, "fallback": "builtins.function", "implicit": false, "is_ellipsis_args": false, "name": "HTML", "ret_type": {".class": "NoneTyp"}, "variables": []}}}}, "tuple_type": null, "type_vars": [], "typeddict_type": null}}, "List": {".class": "SymbolTableNode", "cross_ref": "typing.List", "kind": "Gdef"}, "NewType": {".class": "SymbolTableNode", "cross_ref": "typing.NewType", "kind": "Gdef"}, "Opt": {".class": "SymbolTableNode", "cross_ref": "typing.Optional", "kind": "Gdef"}, "Response": {".class": "SymbolTableNode", "cross_ref": "flask.wrappers.Response", "kind": "Gdef"}, "SearchSession": {".class": "SymbolTableNode", "kind": "Gdef", "node": {".class": "TypeInfo", "_promote": null, "abstract_attributes": [], "bases": ["builtins.object"], "declared_metaclass": null, "defn": {".class": "ClassDef", "fullname": "app.types.SearchSession", "name": "SearchSession", "type_vars": []}, "flags": ["fallback_to_any"], "fullname": "app.types.SearchSession", "metaclass_type": null, "metadata": {}, "module_name": "app.types", "mro": ["app.types.SearchSession", "builtins.object"], "names": {".class": "SymbolTable", "_changes": {".class": "SymbolTableNode", "kind": "Mdef", "node": {".class": "Var", "flags": ["is_initialized_in_class"], "fullname": "app.types.SearchSession._changes", "name": "_changes", "type": {".class": "Instance", "args": ["builtins.str", {".class": "Instance", "args": [{".class": "AnyType", "missing_import_name": null, "source_any": null, "type_of_any": 2}], "type_ref": "builtins.list"}], "type_ref": "builtins.dict"}}}}, "tuple_type": null, "type_vars": [], "typeddict_type": null}}, "Session": {".class": "SymbolTableNode", "kind": "Gdef", "node": {".class": "Var", "flags": ["is_suppressed_import"], "fullname": "app.types.Session", "name": "Session", "type": {".class": "AnyType", "missing_import_name": "app.types.Session", "source_any": null, "type_of_any": 3}}}, "TypeVar": {".class": "SymbolTableNode", "cross_ref": "typing.TypeVar", "kind": "Gdef"}, "URL": {".class": "SymbolTableNode", "kind": "Gdef", "node": {".class": "TypeInfo", "_promote": null, "abstract_attributes": [], "bases": ["builtins.str"], "declared_metaclass": null, "defn": {".class": "ClassDef", "fullname": "app.types.URL", "name": "URL", "type_vars": []}, "flags": ["is_newtype"], "fullname": "app.types.URL", "metaclass_type": null, "metadata": {}, "module_name": "app.types", "mro": ["app.types.URL", "builtins.str", "typing.Sequence", "typing.Collection", "typing.Iterable", "typing.Container", "typing.Reversible", "builtins.object"], "names": {".class": "SymbolTable", "__init__": {".class": "SymbolTableNode", "kind": "Mdef", "node": {".class": "FuncDef", "arg_kinds": [0, 0], "arg_names": ["self", "item"], "flags": [], "fullname": "app.types.URL.__init__", "name": "__init__", "type": {".class": "CallableType", "arg_kinds": [0, 0], "arg_names": ["self", "item"], "arg_types": ["app.types.URL", "builtins.str"], "bound_args": [], "def_extras": {}, "fallback": "builtins.function", "implicit": false, "is_ellipsis_args": false, "name": "URL", "ret_type": {".class": "NoneTyp"}, "variables": []}}}}, "tuple_type": null, "type_vars": [], "typeddict_type": null}}, "Union": {".class": "SymbolTableNode", "cross_ref": "typing.Union", "kind": "Gdef"}, "__doc__": {".class": "SymbolTableNode", "kind": "Gdef", "node": {".class": "Var", "flags": [], "fullname": "app.types.__doc__", "name": "__doc__", "type": "builtins.str"}}, "__file__": {".class": "SymbolTableNode", "kind": "Gdef", "node": {".class": "Var", "flags": [], "fullname": "app.types.__file__", "name": "__file__", "type": "builtins.str"}}, "__name__": {".class": "SymbolTableNode", "kind": "Gdef", "node": {".class": "Var", "flags": [], "fullname": "app.types.__name__", "name": "__name__", "type": "builtins.str"}}, "__package__": {".class": "SymbolTableNode", "kind": "Gdef", "node": {".class": "Var", "flags": [], "fullname": "app.types.__package__", "name": "__package__", "type": "builtins.str"}}, "cast": {".class": "SymbolTableNode", "cross_ref": "typing.cast", "kind": "Gdef"}, "httpResponse": {".class": "SymbolTableNode", "kind": "Gdef", "node": {".class": "TypeInfo", "_promote": null, "abstract_attributes": [], "bases": ["flask.wrappers.Response"], "declared_metaclass": null, "defn": {".class": "ClassDef", "fullname": "app.types.httpResponse", "name": "httpResponse", "type_vars": []}, "flags": [], "fullname": "app.types.httpResponse", "metaclass_type": null, "metadata": {}, "module_name": "app.types", "mro": ["app.types.httpResponse", "flask.wrappers.Response", "werkzeug.wrappers.Response", "werkzeug.wrappers.BaseResponse", "werkzeug.wrappers.ETagResponseMixin", "werkzeug.wrappers.ResponseStreamMixin", "werkzeug.wrappers.CommonResponseDescriptorsMixin", "werkzeug.wrappers.WWWAuthenticateMixin", "flask.wrappers.JSONMixin", "builtins.object"], "names": {".class": "SymbolTable"}, "tuple_type": null, "type_vars": [], "typeddict_type": null}}, "jsonResponse": {".class": "SymbolTableNode", "kind": "Gdef", "node": {".class": "TypeInfo", "_promote": null, "abstract_attributes": [], "bases": ["flask.wrappers.Response"], "declared_metaclass": null, "defn": {".class": "ClassDef", "fullname": "app.types.jsonResponse", "name": "jsonResponse", "type_vars": []}, "flags": [], "fullname": "app.types.jsonResponse", "metaclass_type": null, "metadata": {}, "module_name": "app.types", "mro": ["app.types.jsonResponse", "flask.wrappers.Response", "werkzeug.wrappers.Response", "werkzeug.wrappers.BaseResponse", "werkzeug.wrappers.ETagResponseMixin", "werkzeug.wrappers.ResponseStreamMixin", "werkzeug.wrappers.CommonResponseDescriptorsMixin", "werkzeug.wrappers.WWWAuthenticateMixin", "flask.wrappers.JSONMixin", "builtins.object"], "names": {".class": "SymbolTable"}, "tuple_type": null, "type_vars": [], "typeddict_type": null}}, "jsonType": {".class": "SymbolTableNode", "kind": "Gdef", "node": {".class": "TypeInfo", "_promote": null, "abstract_attributes": [], "bases": [{".class": "Instance", "args": ["builtins.str", {".class": "AnyType", "missing_import_name": null, "source_any": null, "type_of_any": 2}], "type_ref": "builtins.dict"}], "declared_metaclass": null, "defn": {".class": "ClassDef", "fullname": "app.types.jsonType", "name": "jsonType", "type_vars": []}, "flags": ["is_newtype"], "fullname": "app.types.jsonType", "metaclass_type": null, "metadata": {}, "module_name": "app.types", "mro": ["app.types.jsonType", "builtins.dict", "typing.MutableMapping", "typing.Mapping", "typing.Collection", "typing.Iterable", "typing.Container", "builtins.object"], "names": {".class": "SymbolTable", "__init__": {".class": "SymbolTableNode", "kind": "Mdef", "node": {".class": "FuncDef", "arg_kinds": [0, 0], "arg_names": ["self", "item"], "flags": [], "fullname": "app.types.jsonType.__init__", "name": "__init__", "type": {".class": "CallableType", "arg_kinds": [0, 0], "arg_names": ["self", "item"], "arg_types": ["app.types.jsonType", {".class": "Instance", "args": ["builtins.str", {".class": "AnyType", "missing_import_name": null, "source_any": null, "type_of_any": 2}], "type_ref": "builtins.dict"}], "bound_args": [], "def_extras": {}, "fallback": "builtins.function", "implicit": false, "is_ellipsis_args": false, "name": "jsonType", "ret_type": {".class": "NoneTyp"}, "variables": []}}}}, "tuple_type": null, "type_vars": [], "typeddict_type": null}}}, "path": "c:\\Webdev\\dmltests\\flask\\src\\app\\types.py"}